kuaishou_api/__init__.py
kuaishou_api/api.py
kuaishou_api/exception.py
kuaishou_api/tool.py
kuaishou_api/utils.py
kuaishou_api-0.0.5.dist-info/METADATA
kuaishou_api-0.0.5.dist-info/WHEEL
kuaishou_api-0.0.5.dist-info/top_level.txt
kuaishou_api-0.0.5.dist-info/RECORD
